mathics_django/__init__.py
mathics_django/manage.py
mathics_django/server.py
mathics_django/settings.py
mathics_django/test.py
mathics_django/test_django.py
mathics_django/urls.py
mathics_django/version.py
mathics_django/doc/__init__.py
mathics_django/doc/doc.py
mathics_django/doc/utils.py
mathics_django/web/__init__.py
mathics_django/web/authentication.py
mathics_django/web/format.py
mathics_django/web/forms.py
mathics_django/web/models.py
mathics_django/web/urls.py
mathics_django/web/views.py
mathics_django/web/media/css/documentation.css
mathics_django/web/media/css/font-awesome.min.css
mathics_django/web/media/css/message.css
mathics_django/web/media/css/styles.css
mathics_django/web/media/css/styles_ie.css
mathics_django/web/media/css/styles_print.css
mathics_django/web/media/fonts/FontAwesome.otf
mathics_django/web/media/fonts/fontawesome-webfont.eot
mathics_django/web/media/fonts/fontawesome-webfont.svg
mathics_django/web/media/fonts/fontawesome-webfont.ttf
mathics_django/web/media/fonts/fontawesome-webfont.woff
mathics_django/web/media/fonts/fontawesome-webfont.woff2
mathics_django/web/media/img/logo-heptatom.svg
mathics_django/web/media/img/logo-text-nodrop.svg
mathics_django/web/media/img/logo-text.svg
mathics_django/web/media/img/pdf.gif
mathics_django/web/media/img/favicons/android-chrome-192x192.png
mathics_django/web/media/img/favicons/android-chrome-512x512.png
mathics_django/web/media/img/favicons/apple-touch-icon.png
mathics_django/web/media/img/favicons/browserconfig.xml
mathics_django/web/media/img/favicons/favicon-16x16.png
mathics_django/web/media/img/favicons/favicon-32x32.png
mathics_django/web/media/img/favicons/favicon.ico
mathics_django/web/media/img/favicons/manifest.json
mathics_django/web/media/img/favicons/mstile-144x144.png
mathics_django/web/media/img/favicons/mstile-150x150.png
mathics_django/web/media/img/favicons/mstile-310x150.png
mathics_django/web/media/img/favicons/mstile-310x310.png
Mathics_Django-2.1.0.dist-info/AUTHORS.txt
Mathics_Django-2.1.0.dist-info/COPYING.txt
Mathics_Django-2.1.0.dist-info/METADATA
Mathics_Django-2.1.0.dist-info/WHEEL
Mathics_Django-2.1.0.dist-info/entry_points.txt
Mathics_Django-2.1.0.dist-info/top_level.txt
Mathics_Django-2.1.0.dist-info/RECORD
