Metadata-Version: 2.1
Name: Mathics-Django
Version: 2.1.0
Summary: A Django front end for Mathics.
Home-page: https://mathics.org/
Maintainer: Mathics Group
License: GPL
Keywords: Mathematica,Wolfram,Interpreter,Shell,Math,CAS
Platform: UNKNOWN
Classifier: Intended Audience :: Developers
Classifier: Intended Audience :: Science/Research
Classifier: License :: OSI Approved :: GNU General Public License v3 (GPLv3)
Classifier: Programming Language :: Python
Classifier: Programming Language :: Python :: 3.6
Classifier: Programming Language :: Python :: 3.7
Classifier: Programming Language :: Python :: 3.8
Classifier: Programming Language :: Python :: 3.9
Classifier: Programming Language :: Python :: Implementation :: CPython
Classifier: Programming Language :: Python :: Implementation :: PyPy
Classifier: Topic :: Scientific/Engineering
Classifier: Topic :: Scientific/Engineering :: Mathematics
Classifier: Topic :: Scientific/Engineering :: Physics
Classifier: Topic :: Software Development :: Interpreters
Requires-Dist: Mathics-Scanner (<1.2.0,>=1.0.0)
Requires-Dist: Mathics3 (>=2.1.0)
Requires-Dist: django (<3.2,>=3.0)
Requires-Dist: networkx (>=2.5)
Requires-Dist: requests
